HoloCapture/HoloCapture.py
HoloCapture/__init__.py
holocapture-0.1.1.dist-info/licenses/LICENSE
holocapture-0.1.1.dist-info/METADATA
holocapture-0.1.1.dist-info/WHEEL
holocapture-0.1.1.dist-info/top_level.txt
holocapture-0.1.1.dist-info/RECORD
