Metadata-Version: 2.4
Name: HoloCapture
Version: 0.1.1
Summary: An easy way to capture and stream media from multiple cameras, from the screen and urls
Author: Tristan McBride Sr.
Author-email: "Tristan McBride Sr." <142635792+TristanMcBrideSr@users.noreply.github.com>
Project-URL: Homepage, https://github.com/TristanMcBrideSr
Requires-Python: >=3.10
License-File: LICENSE
Requires-Dist: opencv-python
Requires-Dist: numpy
Requires-Dist: Pillow
Requires-Dist: requests
Requires-Dist: MediaCapture
Requires-Dist: mss
Dynamic: author
Dynamic: license-file
